carbonado/__init__.py
carbonado/_clique.py
carbonado/start.proc.py
carbonado/_license/licenses/gpl-3.0-standalone.html
carbonado/_status/status.proc.py
carbonado/_status/checks/1/status_1.py
carbonado/basin/__init__.py
carbonado/basin/treasury.py
carbonado/climate/__init__.py
carbonado/modules/add_glob_to_paths.py
carbonado/modules/parse_extensions.py
carbonado-1.0.4.dist-info/METADATA
carbonado-1.0.4.dist-info/WHEEL
carbonado-1.0.4.dist-info/entry_points.txt
carbonado-1.0.4.dist-info/top_level.txt
carbonado-1.0.4.dist-info/RECORD
