Metadata-Version: 2.1
Name: carbonado
Version: 1.0.4
Summary: The best documentation framework every created.
License: GPL 3.0
Project-URL: GitLab, https://gitlab.com/offline-money/squash-1/carbonado
Requires-Dist: onesie
Requires-Dist: law-dictionary
Requires-Dist: clique
Requires-Dist: esprima
Requires-Dist: mako
Requires-Dist: flask
Requires-Dist: jsonschema
Requires-Dist: rich
